LICENSE
MANIFEST.in
README.rst
VERSION
setup.cfg
setup.py
sprockets_postgres.py
sprockets_postgres.egg-info/PKG-INFO
sprockets_postgres.egg-info/SOURCES.txt
sprockets_postgres.egg-info/dependency_links.txt
sprockets_postgres.egg-info/requires.txt
sprockets_postgres.egg-info/top_level.txt
sprockets_postgres.egg-info/zip-safe