Metadata-Version: 2.1
Name: sprockets-postgres
Version: 1.3.3
Summary: An asynchronous Postgres client and mixin for Tornado applications
Home-page: https://github.com/sprockets/sprockets-postgres
License: BSD 3-Clause License
Project-URL: Bug Tracker, https://github.com/sprockets/sprockets-postgres/issues
Project-URL: Documentation, https://sprockets-postgres.readthedocs.io
Project-URL: Source Code, https://github.com/sprockets/sprockets-postgres/
Keywords: postgres,python3,tornado
Platform: UNKNOWN
Classifier: Development Status :: 3 - Alpha
Classifier: Intended Audience :: Developers
Classifier: License :: OSI Approved :: BSD License
Classifier: Natural Language :: English
Classifier: Operating System :: OS Independent
Classifier: Programming Language :: Python :: 3
Classifier: Programming Language :: Python :: 3.7
Classifier: Programming Language :: Python :: 3.8
Classifier: Topic :: Communications
Classifier: Topic :: Internet
Classifier: Topic :: Software Development
Classifier: Typing :: Typed
Provides-Extra: testing
